[{
    "id": 24889,
    "fileName": "1",
    "size": 101998,
    "fileType": "jpg",
    "filePath": "G:/100MEDIA/selected/1.jpg" 
},
{
    "id": 21591,
    "fileName": "1",
    "size": 241416,
    "fileType": "jpg",
    "filePath": "G:/100MEDIA/facebook/facebook-album-757022910989410/1.jpg" 
},
{
    "id": 21533,
    "fileName": "1",
    "size": 185142,
    "fileType": "jpg",
    "filePath": "G:/100MEDIA/facebook/facebook-album-587134984644871/1.jpg" 
},
{
    "id": 21592,
    "fileName": "10",
    "size": 150622,
    "fileType": "jpg",
    "filePath": "G:/100MEDIA/facebook/facebook-album-757022910989410/10.jpg" 
},
{
    "id": 21534,
    "fileName": "10",
    "size": 189844,
    "fileType": "jpg",
    "filePath": "G:/100MEDIA/facebook/facebook-album-587134984644871/10.jpg" 
},
{
    "id": 21593,
    "fileName": "11",
    "size": 77447,
    "fileType": "jpg",
    "filePath": "G:/100MEDIA/facebook/facebook-album-757022910989410/11.jpg" 
},
{
    "id": 21535,
    "fileName": "11",
    "size": 213209,
    "fileType": "jpg",
    "filePath": "G:/100MEDIA/facebook/facebook-album-587134984644871/11.jpg" 
},
{
    "id": 21594,
    "fileName": "12",
    "size": 237889,
    "fileType": "jpg",
    "filePath": "G:/100MEDIA/facebook/facebook-album-757022910989410/12.jpg" 
},
{
    "id": 21536,
    "fileName": "12",
    "size": 152910,
    "fileType": "jpg",
    "filePath": "G:/100MEDIA/facebook/facebook-album-587134984644871/12.jpg" 
},
{
    "id": 21595,
    "fileName": "13",
    "size": 276872,
    "fileType": "jpg",
    "filePath": "G:/100MEDIA/facebook/facebook-album-757022910989410/13.jpg" 
},
{
    "id": 21537,
    "fileName": "13",
    "size": 135754,
    "fileType": "jpg",
    "filePath": "G:/100MEDIA/facebook/facebook-album-587134984644871/13.jpg" 
},
{
    "id": 21596,
    "fileName": "14",
    "size": 289731,
    "fileType": "jpg",
    "filePath": "G:/100MEDIA/facebook/facebook-album-757022910989410/14.jpg" 
},
{
    "id": 21538,
    "fileName": "14",
    "size": 124493,
    "fileType": "jpg",
    "filePath": "G:/100MEDIA/facebook/facebook-album-587134984644871/14.jpg" 
}
]